multimethod/__init__.py
multimethod/py.typed
multimethod-1.9.dist-info/LICENSE.txt
multimethod-1.9.dist-info/METADATA
multimethod-1.9.dist-info/WHEEL
multimethod-1.9.dist-info/top_level.txt
multimethod-1.9.dist-info/RECORD
