Metadata-Version: 2.1
Name: multimethod
Version: 1.9
Summary: Multiple argument dispatching.
Author-email: Aric Coady <aric.coady@gmail.com>
License: Copyright 2022 Aric Coady
Project-URL: Homepage, https://github.com/coady/multimethod
Project-URL: Documentation, https://coady.github.io/multimethod
Keywords: multiple,dispatch,multidispatch,generic,functions,methods,overload
Classifier: Development Status :: 5 - Production/Stable
Classifier: Intended Audience :: Developers
Classifier: License :: OSI Approved :: Apache Software License
Classifier: Operating System :: OS Independent
Classifier: Programming Language :: Python :: 3
Classifier: Programming Language :: Python :: 3.7
Classifier: Programming Language :: Python :: 3.8
Classifier: Programming Language :: Python :: 3.9
Classifier: Programming Language :: Python :: 3.10
Classifier: Programming Language :: Python :: 3.11
Classifier: Topic :: Software Development :: Libraries :: Python Modules
Classifier: Typing :: Typed
Requires-Python: >=3.7
License-File: LICENSE.txt
